polly/__init__.py
polly/config/__init__.py
polly/config/handler.py
polly/core/__init__.py
polly/core/classes/__init__.py
polly/core/classes/candidate_network.py
polly/core/classes/keyword_match.py
polly/core/classes/query_match.py
polly/core/handlers/__init__.py
polly/core/handlers/candidate_network_handler.py
polly/core/handlers/keyword_match_handler.py
polly/core/handlers/query_match_handler.py
polly/evaluation/__init__.py
polly/evaluation/handler.py
polly/evaluation/result.py
polly/index/__init__.py
polly/index/babel/__init__.py
polly/index/babel/hash.py
polly/index/handler.py
polly/index/schema_index.py
polly/index/type_index.py
polly/index/value_index.py
polly/llm/chat.py
polly/llm/describer.py
polly/llm/matcher.py
polly/llm/ranker.py
polly/main.py
polly/sources/__init__.py
polly/sources/csv/__init__.py
polly/sources/csv/handler.py
polly/sources/csv/iter.py
polly/sources/enum.py
polly/sources/handler.py
polly/sources/mongo/__init__.py
polly/sources/mongo/handler.py
polly/sources/mongo/iter.py
polly/sources/mongo/utils/__init__.py
polly/sources/mongo/utils/attribute_tree_generator.py
polly/sources/mongo/utils/dict_to_tuple.py
polly/sources/mongo/utils/functions.py
polly/sources/mongo/utils/query_builder.py
polly/sources/mongo/utils/result.py
polly/sources/mongo/utils/traverser.py
polly/sources/postgres/__init__.py
polly/sources/postgres/handler.py
polly/sources/postgres/iter.py
polly/sources/utils/interfaces.py
polly/utils/__init__.py
polly/utils/data_source_enum.py
polly/utils/dataframe_sort.py
polly/utils/get_logger.py
polly/utils/graph.py
polly/utils/keyword_query.py
polly/utils/memory.py
polly/utils/path.py
polly/utils/printmd.py
polly/utils/result.py
polly/utils/schema_graph.py
polly/utils/shift_tab.py
polly/utils/similarity.py
polly/utils/tf_iaf.py
polly/utils/tokenizer.py
pollyd-0.0.1.dist-info/METADATA
pollyd-0.0.1.dist-info/WHEEL
pollyd-0.0.1.dist-info/RECORD
